pyvesteltv/__init__.py
pyvesteltv/broadcast.py
pyvesteltv/pyvesteltv.py
pyvesteltv/pyvesteltv2 – kopio.py
pyvesteltv/pyvesteltv_old.py
pyvesteltv-0.1.5.dist-info/LICENSE
pyvesteltv-0.1.5.dist-info/METADATA
pyvesteltv-0.1.5.dist-info/WHEEL
pyvesteltv-0.1.5.dist-info/top_level.txt
pyvesteltv-0.1.5.dist-info/RECORD
