Metadata-Version: 2.1
Name: pyvesteltv
Version: 0.1.5
Summary: A library to interface with some Vestel TV sets
Home-page: https://github.com/T3m3z/pyvesteltv
Author: Teemu Mikkonen
Author-email: teemu.mikkonen@iki.fi
License: MIT
Platform: UNKNOWN
Requires-Dist: websockets (>=6.0)
